{
    "id":  "logh7-1080p-client-patch",
    "schemaVersion":  1,
    "status":  "available",
    "purpose":  "Keep the original 644x484 login panel and apply native 1920x1080 layouts only after login.",
    "resolutionBoundary":  {
                                "loginClientArea":  "644x484-original",
                                "postLoginClientArea":  "1920x1080-native"
                            },
    "provenance":  {
                       "sourceRevision":  "c354b4e6^",
                       "descriptors":  [
                                           "RE/tools/client_patches/lobby-res.json",
                                           "RE/tools/client_patches/lobby-native-layout-v2.json",
                                           "RE/tools/client_patches/charsel-recenter.json"
                                       ],
                       "caveat":  "The 59 post-login byte ranges were verified against the target EXE. The login panel is deliberately unpatched; lobby-native-layout-v2 and charsel-recenter still require live visual QA."
                   },
    "targetExe":  {
                      "name":  "g7mtclient.exe",
                      "sha256":  "5bdd64f1f9a8cca93f5b1002291d6a2c7e8f5ce555b062b8cb48337b96277d89",
                      "imageBase":  4194304,
                      "size":  3956736,
                      "pathHints":  [
                                        "artifacts/logh7-install/**/exe/g7mtclient.exe"
                                    ],
                      "note":  "CP932-compatible installed client; applying this manifest must not restore the earlier mojibake-producing charset bytes."
                  },
    "expectedPatchedSha256":  "825635783a9fb663ae3b9a2ecf8d4b74df648322256c57ee32f6426c42a23f22",
    "policy":  {
                   "sameLengthOnly":  true,
                   "requireOriginalBytes":  true,
                   "requireRollbackBytes":  true,
                   "supportsDryRun":  true,
                   "neverOverwriteOriginal":  false
               },
   "patches":  [
                   {
                       "id":  "lobby-res-01",
                        "sourceExeSha256":  "5bdd64f1f9a8cca93f5b1002291d6a2c7e8f5ce555b062b8cb48337b96277d89",
                        "addressKind":  "offset",
                        "offset":  1156928,
                        "virtualAddressHex":  "0x51a740",
                        "originalBytes":  "6800040000",
                        "patchedBytes":  "6880070000",
                        "rollbackBytes":  "6800040000",
                        "reason":  "lobby width push 0x400(1024) -\u003e 1920"
                    },
                    {
                        "id":  "lobby-res-02",
                        "sourceExeSha256":  "5bdd64f1f9a8cca93f5b1002291d6a2c7e8f5ce555b062b8cb48337b96277d89",
                        "addressKind":  "offset",
                        "offset":  1156949,
                        "virtualAddressHex":  "0x51a755",
                        "originalBytes":  "6800040000",
                        "patchedBytes":  "6880070000",
                        "rollbackBytes":  "6800040000",
                        "reason":  "lobby width push 0x400(1024) -\u003e 1920"
                    },
                    {
                        "id":  "lobby-res-03",
                        "sourceExeSha256":  "5bdd64f1f9a8cca93f5b1002291d6a2c7e8f5ce555b062b8cb48337b96277d89",
                        "addressKind":  "offset",
                        "offset":  1157359,
                        "virtualAddressHex":  "0x51a8ef",
                        "originalBytes":  "6800040000",
                        "patchedBytes":  "6880070000",
                        "rollbackBytes":  "6800040000",
                        "reason":  "lobby width push 0x400(1024) -\u003e 1920"
                    },
                    {
                        "id":  "lobby-res-04",
                        "sourceExeSha256":  "5bdd64f1f9a8cca93f5b1002291d6a2c7e8f5ce555b062b8cb48337b96277d89",
                        "addressKind":  "offset",
                        "offset":  1157380,
                        "virtualAddressHex":  "0x51a904",
                        "originalBytes":  "6800040000",
                        "patchedBytes":  "6880070000",
                        "rollbackBytes":  "6800040000",
                        "reason":  "lobby width push 0x400(1024) -\u003e 1920"
                    },
                    {
                        "id":  "lobby-res-05",
                        "sourceExeSha256":  "5bdd64f1f9a8cca93f5b1002291d6a2c7e8f5ce555b062b8cb48337b96277d89",
                        "addressKind":  "offset",
                        "offset":  1156923,
                        "virtualAddressHex":  "0x51a73b",
                        "originalBytes":  "6800030000",
                        "patchedBytes":  "6838040000",
                        "rollbackBytes":  "6800030000",
                        "reason":  "lobby height push 0x300(768) -\u003e 1080"
                    },
                    {
                        "id":  "lobby-res-06",
                        "sourceExeSha256":  "5bdd64f1f9a8cca93f5b1002291d6a2c7e8f5ce555b062b8cb48337b96277d89",
                        "addressKind":  "offset",
                        "offset":  1156944,
                        "virtualAddressHex":  "0x51a750",
                        "originalBytes":  "6800030000",
                        "patchedBytes":  "6838040000",
                        "rollbackBytes":  "6800030000",
                        "reason":  "lobby height push 0x300(768) -\u003e 1080"
                    },
                    {
                        "id":  "lobby-res-07",
                        "sourceExeSha256":  "5bdd64f1f9a8cca93f5b1002291d6a2c7e8f5ce555b062b8cb48337b96277d89",
                        "addressKind":  "offset",
                        "offset":  1157354,
                        "virtualAddressHex":  "0x51a8ea",
                        "originalBytes":  "6800030000",
                        "patchedBytes":  "6838040000",
                        "rollbackBytes":  "6800030000",
                        "reason":  "lobby height push 0x300(768) -\u003e 1080"
                    },
                    {
                        "id":  "lobby-res-08",
                        "sourceExeSha256":  "5bdd64f1f9a8cca93f5b1002291d6a2c7e8f5ce555b062b8cb48337b96277d89",
                        "addressKind":  "offset",
                        "offset":  1157375,
                        "virtualAddressHex":  "0x51a8ff",
                        "originalBytes":  "6800030000",
                        "patchedBytes":  "6838040000",
                        "rollbackBytes":  "6800030000",
                        "reason":  "lobby height push 0x300(768) -\u003e 1080"
                    },
                    {
                        "id":  "lobby-native-layout-v2-01",
                        "sourceExeSha256":  "5bdd64f1f9a8cca93f5b1002291d6a2c7e8f5ce555b062b8cb48337b96277d89",
                        "addressKind":  "offset",
                        "offset":  1165712,
                        "virtualAddressHex":  "0x0051c990",
                        "originalBytes":  "b8db020000",
                        "patchedBytes":  "b89b040000",
                        "rollbackBytes":  "b8db020000",
                        "reason":  "eax right-column x (feeds 5 slots) 731 -\u003e 1179 (1920-center, DX=448)"
                    },
                    {
                        "id":  "lobby-native-layout-v2-02",
                        "sourceExeSha256":  "5bdd64f1f9a8cca93f5b1002291d6a2c7e8f5ce555b062b8cb48337b96277d89",
                        "addressKind":  "offset",
                        "offset":  1165717,
                        "virtualAddressHex":  "0x0051c995",
                        "originalBytes":  "b95d020000",
                        "patchedBytes":  "b91d040000",
                        "rollbackBytes":  "b95d020000",
                        "reason":  "ecx middle-column x (feeds 3 slots) 605 -\u003e 1053 (1920-center, DX=448)"
                    },
                    {
                        "id":  "lobby-native-layout-v2-03",
                        "sourceExeSha256":  "5bdd64f1f9a8cca93f5b1002291d6a2c7e8f5ce555b062b8cb48337b96277d89",
                        "addressKind":  "offset",
                        "offset":  1165770,
                        "virtualAddressHex":  "0x0051c9ca",
                        "originalBytes":  "c74424080f000000",
                        "patchedBytes":  "c7442408cf010000",
                        "rollbackBytes":  "c74424080f000000",
                        "reason":  "left-column anchor x 15 -\u003e 463 (1920-center, DX=448)"
                    },
                    {
                        "id":  "lobby-native-layout-v2-04",
                        "sourceExeSha256":  "5bdd64f1f9a8cca93f5b1002291d6a2c7e8f5ce555b062b8cb48337b96277d89",
                        "addressKind":  "offset",
                        "offset":  1165778,
                        "virtualAddressHex":  "0x0051c9d2",
                        "originalBytes":  "c74424102c010000",
                        "patchedBytes":  "c7442410ec020000",
                        "rollbackBytes":  "c74424102c010000",
                        "reason":  "main lobby panel anchor x 300 -\u003e 748 (1920-center, DX=448)"
                    },
                    {
                        "id":  "lobby-native-layout-v2-05",
                        "sourceExeSha256":  "5bdd64f1f9a8cca93f5b1002291d6a2c7e8f5ce555b062b8cb48337b96277d89",
                        "addressKind":  "offset",
                        "offset":  1165699,
                        "virtualAddressHex":  "0x0051c983",
                        "originalBytes":  "b886000000",
                        "patchedBytes":  "b822010000",
                        "rollbackBytes":  "b886000000",
                        "reason":  "common-row y 134 -\u003e 290 (1080-center, DY=156)"
                    },
                    {
                        "id":  "lobby-native-layout-v2-06",
                        "sourceExeSha256":  "5bdd64f1f9a8cca93f5b1002291d6a2c7e8f5ce555b062b8cb48337b96277d89",
                        "addressKind":  "offset",
                        "offset":  1165786,
                        "virtualAddressHex":  "0x0051c9da",
                        "originalBytes":  "c744241cce000000",
                        "patchedBytes":  "c744241c6a010000",
                        "rollbackBytes":  "c744241cce000000",
                        "reason":  "submenu row y 206 -\u003e 362 (1080-center, DY=156)"
                    },
                    {
                        "id":  "lobby-native-layout-v2-07",
                        "sourceExeSha256":  "5bdd64f1f9a8cca93f5b1002291d6a2c7e8f5ce555b062b8cb48337b96277d89",
                        "addressKind":  "offset",
                        "offset":  1165794,
                        "virtualAddressHex":  "0x0051c9e2",
                        "originalBytes":  "c7442424f3000000",
                        "patchedBytes":  "c74424248f010000",
                        "rollbackBytes":  "c7442424f3000000",
                        "reason":  "submenu row y 243 -\u003e 399 (1080-center, DY=156)"
                    },
                    {
                        "id":  "lobby-native-layout-v2-08",
                        "sourceExeSha256":  "5bdd64f1f9a8cca93f5b1002291d6a2c7e8f5ce555b062b8cb48337b96277d89",
                        "addressKind":  "offset",
                        "offset":  1165802,
                        "virtualAddressHex":  "0x0051c9ea",
                        "originalBytes":  "c744242c14010000",
                        "patchedBytes":  "c744242cb0010000",
                        "rollbackBytes":  "c744242c14010000",
                        "reason":  "submenu row y 276 -\u003e 432 (1080-center, DY=156)"
                    },
                    {
                        "id":  "lobby-native-layout-v2-09",
                        "sourceExeSha256":  "5bdd64f1f9a8cca93f5b1002291d6a2c7e8f5ce555b062b8cb48337b96277d89",
                        "addressKind":  "offset",
                        "offset":  1165810,
                        "virtualAddressHex":  "0x0051c9f2",
                        "originalBytes":  "c744243433010000",
                        "patchedBytes":  "c7442434cf010000",
                        "rollbackBytes":  "c744243433010000",
                        "reason":  "submenu row y 307 -\u003e 463 (1080-center, DY=156)"
                    },
                    {
                        "id":  "lobby-native-layout-v2-10",
                        "sourceExeSha256":  "5bdd64f1f9a8cca93f5b1002291d6a2c7e8f5ce555b062b8cb48337b96277d89",
                        "addressKind":  "offset",
                        "offset":  1165818,
                        "virtualAddressHex":  "0x0051c9fa",
                        "originalBytes":  "c744243c51010000",
                        "patchedBytes":  "c744243ced010000",
                        "rollbackBytes":  "c744243c51010000",
                        "reason":  "submenu row y 337 -\u003e 493 (1080-center, DY=156)"
                    },
                    {
                        "id":  "lobby-native-layout-v2-11",
                        "sourceExeSha256":  "5bdd64f1f9a8cca93f5b1002291d6a2c7e8f5ce555b062b8cb48337b96277d89",
                        "addressKind":  "offset",
                        "offset":  1165826,
                        "virtualAddressHex":  "0x0051ca02",
                        "originalBytes":  "c74424447c010000",
                        "patchedBytes":  "c744244418020000",
                        "rollbackBytes":  "c74424447c010000",
                        "reason":  "submenu row y 380 -\u003e 536 (1080-center, DY=156)"
                    },
                    {
                        "id":  "lobby-native-layout-v2-12",
                        "sourceExeSha256":  "5bdd64f1f9a8cca93f5b1002291d6a2c7e8f5ce555b062b8cb48337b96277d89",
                        "addressKind":  "offset",
                        "offset":  1165834,
                        "virtualAddressHex":  "0x0051ca0a",
                        "originalBytes":  "c744244c9e010000",
                        "patchedBytes":  "c744244c3a020000",
                        "rollbackBytes":  "c744244c9e010000",
                        "reason":  "submenu row y 414 -\u003e 570 (1080-center, DY=156)"
                    },
                    {
                        "id":  "lobby-native-layout-v2-13",
                        "sourceExeSha256":  "5bdd64f1f9a8cca93f5b1002291d6a2c7e8f5ce555b062b8cb48337b96277d89",
                        "addressKind":  "offset",
                        "offset":  1165842,
                        "virtualAddressHex":  "0x0051ca12",
                        "originalBytes":  "c7442454bd010000",
                        "patchedBytes":  "c744245459020000",
                        "rollbackBytes":  "c7442454bd010000",
                        "reason":  "submenu row y 445 -\u003e 601 (1080-center, DY=156)"
                    },
                    {
                        "id":  "charsel-recenter-01",
                        "sourceExeSha256":  "5bdd64f1f9a8cca93f5b1002291d6a2c7e8f5ce555b062b8cb48337b96277d89",
                        "addressKind":  "offset",
                        "offset":  1173838,
                        "virtualAddressHex":  "0x0051e94e",
                        "originalBytes":  "c74424302c010000",
                        "patchedBytes":  "c74424305c020000",
                        "rollbackBytes":  "c74424302c010000",
                        "reason":  "panel container anchor X 300 -\u003e 604 (center of 1920: (1920-711)/2). FUN_00507a50 local_2c8."
                    },
                    {
                        "id":  "charsel-recenter-02",
                        "sourceExeSha256":  "5bdd64f1f9a8cca93f5b1002291d6a2c7e8f5ce555b062b8cb48337b96277d89",
                        "addressKind":  "offset",
                        "offset":  1173846,
                        "virtualAddressHex":  "0x0051e956",
                        "originalBytes":  "c744243486000000",
                        "patchedBytes":  "c744243418010000",
                        "rollbackBytes":  "c744243486000000",
                        "reason":  "panel container anchor Y 134 -\u003e 280 (center of 1080: (1080-520)/2). FUN_00507a50 local_2c4."
                    },
                    {
                        "id":  "charsel-recenter-03",
                        "sourceExeSha256":  "5bdd64f1f9a8cca93f5b1002291d6a2c7e8f5ce555b062b8cb48337b96277d89",
                        "addressKind":  "offset",
                        "offset":  1170612,
                        "virtualAddressHex":  "0x0051dcb4",
                        "originalBytes":  "c74424282c010000",
                        "patchedBytes":  "c74424285c020000",
                        "rollbackBytes":  "c74424282c010000",
                        "reason":  "content panel FUN_0051dc00 anchor X 300-\u003e604 (+304). 507a50 setter 직전 확증."
                    },
                    {
                        "id":  "charsel-recenter-04",
                        "sourceExeSha256":  "5bdd64f1f9a8cca93f5b1002291d6a2c7e8f5ce555b062b8cb48337b96277d89",
                        "addressKind":  "offset",
                        "offset":  1170620,
                        "virtualAddressHex":  "0x0051dcbc",
                        "originalBytes":  "c744242c86000000",
                        "patchedBytes":  "c744242c18010000",
                        "rollbackBytes":  "c744242c86000000",
                        "reason":  "content panel FUN_0051dc00 anchor Y 134-\u003e280 (+146)."
                    },
                    {
                        "id":  "charsel-recenter-05",
                        "sourceExeSha256":  "5bdd64f1f9a8cca93f5b1002291d6a2c7e8f5ce555b062b8cb48337b96277d89",
                        "addressKind":  "offset",
                        "offset":  1171761,
                        "virtualAddressHex":  "0x0051e131",
                        "originalBytes":  "c744242c2c010000",
                        "patchedBytes":  "c744242c5c020000",
                        "rollbackBytes":  "c744242c2c010000",
                        "reason":  "content panel FUN_0051dd80 anchor X 300-\u003e604 (+304)."
                    },
                    {
                        "id":  "charsel-recenter-06",
                        "sourceExeSha256":  "5bdd64f1f9a8cca93f5b1002291d6a2c7e8f5ce555b062b8cb48337b96277d89",
                        "addressKind":  "offset",
                        "offset":  1171769,
                        "virtualAddressHex":  "0x0051e139",
                        "originalBytes":  "c744243086000000",
                        "patchedBytes":  "c744243018010000",
                        "rollbackBytes":  "c744243086000000",
                        "reason":  "content panel FUN_0051dd80 anchor Y 134-\u003e280 (+146)."
                    },
                    {
                        "id":  "charsel-recenter-07",
                        "sourceExeSha256":  "5bdd64f1f9a8cca93f5b1002291d6a2c7e8f5ce555b062b8cb48337b96277d89",
                        "addressKind":  "offset",
                        "offset":  1178823,
                        "virtualAddressHex":  "0x0051fcc7",
                        "originalBytes":  "c744242c2c010000",
                        "patchedBytes":  "c744242c5c020000",
                        "rollbackBytes":  "c744242c2c010000",
                        "reason":  "8단계 폼 내용 패널 FUN_0051f8b0 MAIN anchor X 300-\u003e604 (+304). 진영/이름/값슬롯 origin."
                    },
                    {
                        "id":  "charsel-recenter-08",
                        "sourceExeSha256":  "5bdd64f1f9a8cca93f5b1002291d6a2c7e8f5ce555b062b8cb48337b96277d89",
                        "addressKind":  "offset",
                        "offset":  1178831,
                        "virtualAddressHex":  "0x0051fccf",
                        "originalBytes":  "c744243086000000",
                        "patchedBytes":  "c744243018010000",
                        "rollbackBytes":  "c744243086000000",
                        "reason":  "8단계 폼 내용 패널 FUN_0051f8b0 MAIN anchor Y 134-\u003e280 (+146)."
                    },
                    {
                        "id":  "charsel-recenter-09",
                        "sourceExeSha256":  "5bdd64f1f9a8cca93f5b1002291d6a2c7e8f5ce555b062b8cb48337b96277d89",
                        "addressKind":  "offset",
                        "offset":  1182960,
                        "virtualAddressHex":  "0x00520cf0",
                        "originalBytes":  "81c12c010000",
                        "patchedBytes":  "81c15c020000",
                        "rollbackBytes":  "81c12c010000",
                        "reason":  "FUN_0051f8b0 행 레이아웃 상대베이스 add ecx,0x12c(300)-\u003e0x25c(604). 값슬롯 row origin X."
                    },
                    {
                        "id":  "charsel-recenter-10",
                        "sourceExeSha256":  "5bdd64f1f9a8cca93f5b1002291d6a2c7e8f5ce555b062b8cb48337b96277d89",
                        "addressKind":  "offset",
                        "offset":  1182974,
                        "virtualAddressHex":  "0x00520cfe",
                        "originalBytes":  "0586000000",
                        "patchedBytes":  "0518010000",
                        "rollbackBytes":  "0586000000",
                        "reason":  "FUN_0051f8b0 행 레이아웃 상대베이스 add eax,0x86(134)-\u003e0x118(280). 값슬롯 row origin Y."
                    },
                    {
                        "id":  "charsel-recenter-11",
                        "sourceExeSha256":  "5bdd64f1f9a8cca93f5b1002291d6a2c7e8f5ce555b062b8cb48337b96277d89",
                        "addressKind":  "offset",
                        "offset":  1674194,
                        "virtualAddressHex":  "0x00598bd2",
                        "originalBytes":  "c74424282c010000",
                        "patchedBytes":  "c74424285c020000",
                        "rollbackBytes":  "c74424282c010000",
                        "reason":  "FUN_005989f0 step-panel X +304"
                    },
                    {
                        "id":  "charsel-recenter-12",
                        "sourceExeSha256":  "5bdd64f1f9a8cca93f5b1002291d6a2c7e8f5ce555b062b8cb48337b96277d89",
                        "addressKind":  "offset",
                        "offset":  1674202,
                        "virtualAddressHex":  "0x00598bda",
                        "originalBytes":  "c744242c86000000",
                        "patchedBytes":  "c744242cf2000000",
                        "rollbackBytes":  "c744242c86000000",
                        "reason":  "FUN_005989f0 step-panel Y 134-\u003e242 (+108). PIL측정: 콘텐츠가 프레임중심보다 38px 아래 → 위로 38 보정(280→242) center-to-center."
                    },
                    {
                        "id":  "charsel-recenter-13",
                        "sourceExeSha256":  "5bdd64f1f9a8cca93f5b1002291d6a2c7e8f5ce555b062b8cb48337b96277d89",
                        "addressKind":  "offset",
                        "offset":  1675730,
                        "virtualAddressHex":  "0x005991d2",
                        "originalBytes":  "c74424282c010000",
                        "patchedBytes":  "c74424285c020000",
                        "rollbackBytes":  "c74424282c010000",
                        "reason":  "FUN_00598ff0 step-panel X +304"
                    },
                    {
                        "id":  "charsel-recenter-14",
                        "sourceExeSha256":  "5bdd64f1f9a8cca93f5b1002291d6a2c7e8f5ce555b062b8cb48337b96277d89",
                        "addressKind":  "offset",
                        "offset":  1675738,
                        "virtualAddressHex":  "0x005991da",
                        "originalBytes":  "c744242c86000000",
                        "patchedBytes":  "c744242c18010000",
                        "rollbackBytes":  "c744242c86000000",
                        "reason":  "FUN_00598ff0 step-panel Y +146"
                    },
                    {
                        "id":  "charsel-recenter-15",
                        "sourceExeSha256":  "5bdd64f1f9a8cca93f5b1002291d6a2c7e8f5ce555b062b8cb48337b96277d89",
                        "addressKind":  "offset",
                        "offset":  1677266,
                        "virtualAddressHex":  "0x005997d2",
                        "originalBytes":  "c74424282c010000",
                        "patchedBytes":  "c74424285c020000",
                        "rollbackBytes":  "c74424282c010000",
                        "reason":  "FUN_005995f0 step-panel X +304"
                    },
                    {
                        "id":  "charsel-recenter-16",
                        "sourceExeSha256":  "5bdd64f1f9a8cca93f5b1002291d6a2c7e8f5ce555b062b8cb48337b96277d89",
                        "addressKind":  "offset",
                        "offset":  1677274,
                        "virtualAddressHex":  "0x005997da",
                        "originalBytes":  "c744242c86000000",
                        "patchedBytes":  "c744242c18010000",
                        "rollbackBytes":  "c744242c86000000",
                        "reason":  "FUN_005995f0 step-panel Y +146"
                    },
                    {
                        "id":  "charsel-recenter-17",
                        "sourceExeSha256":  "5bdd64f1f9a8cca93f5b1002291d6a2c7e8f5ce555b062b8cb48337b96277d89",
                        "addressKind":  "offset",
                        "offset":  1679216,
                        "virtualAddressHex":  "0x00599f70",
                        "originalBytes":  "c74424282c010000",
                        "patchedBytes":  "c74424285c020000",
                        "rollbackBytes":  "c74424282c010000",
                        "reason":  "FUN_00599e10 step-panel X +304"
                    },
                    {
                        "id":  "charsel-recenter-18",
                        "sourceExeSha256":  "5bdd64f1f9a8cca93f5b1002291d6a2c7e8f5ce555b062b8cb48337b96277d89",
                        "addressKind":  "offset",
                        "offset":  1679224,
                        "virtualAddressHex":  "0x00599f78",
                        "originalBytes":  "c744242c86000000",
                        "patchedBytes":  "c744242c18010000",
                        "rollbackBytes":  "c744242c86000000",
                        "reason":  "FUN_00599e10 step-panel Y +146"
                    },
                    {
                        "id":  "charsel-recenter-19",
                        "sourceExeSha256":  "5bdd64f1f9a8cca93f5b1002291d6a2c7e8f5ce555b062b8cb48337b96277d89",
                        "addressKind":  "offset",
                        "offset":  1681505,
                        "virtualAddressHex":  "0x0059a861",
                        "originalBytes":  "c74424642c010000",
                        "patchedBytes":  "c74424645c020000",
                        "rollbackBytes":  "c74424642c010000",
                        "reason":  "FUN_0059a5e0 step-panel X +304 (disp 0x64)"
                    },
                    {
                        "id":  "charsel-recenter-20",
                        "sourceExeSha256":  "5bdd64f1f9a8cca93f5b1002291d6a2c7e8f5ce555b062b8cb48337b96277d89",
                        "addressKind":  "offset",
                        "offset":  1681513,
                        "virtualAddressHex":  "0x0059a869",
                        "originalBytes":  "c744246886000000",
                        "patchedBytes":  "c744246818010000",
                        "rollbackBytes":  "c744246886000000",
                        "reason":  "FUN_0059a5e0 step-panel Y +146 (disp 0x68)"
                    },
                    {
                        "id":  "charsel-recenter-21",
                        "sourceExeSha256":  "5bdd64f1f9a8cca93f5b1002291d6a2c7e8f5ce555b062b8cb48337b96277d89",
                        "addressKind":  "offset",
                        "offset":  1684567,
                        "virtualAddressHex":  "0x0059b457",
                        "originalBytes":  "c744242c2c010000",
                        "patchedBytes":  "c744242c5c020000",
                        "rollbackBytes":  "c744242c2c010000",
                        "reason":  "FUN_0059b090 초상화 패널 X +304"
                    },
                    {
                        "id":  "charsel-recenter-22",
                        "sourceExeSha256":  "5bdd64f1f9a8cca93f5b1002291d6a2c7e8f5ce555b062b8cb48337b96277d89",
                        "addressKind":  "offset",
                        "offset":  1684575,
                        "virtualAddressHex":  "0x0059b45f",
                        "originalBytes":  "c744243086000000",
                        "patchedBytes":  "c744243018010000",
                        "rollbackBytes":  "c744243086000000",
                        "reason":  "FUN_0059b090 초상화 패널 Y +146"
                    },
                    {
                        "id":  "charsel-recenter-23",
                        "sourceExeSha256":  "5bdd64f1f9a8cca93f5b1002291d6a2c7e8f5ce555b062b8cb48337b96277d89",
                        "addressKind":  "offset",
                        "offset":  1686593,
                        "virtualAddressHex":  "0x0059bc41",
                        "originalBytes":  "c74424342c010000",
                        "patchedBytes":  "c74424345c020000",
                        "rollbackBytes":  "c74424342c010000",
                        "reason":  "FUN_0059b970 step-panel X +304 (disp 0x34)"
                    },
                    {
                        "id":  "charsel-recenter-24",
                        "sourceExeSha256":  "5bdd64f1f9a8cca93f5b1002291d6a2c7e8f5ce555b062b8cb48337b96277d89",
                        "addressKind":  "offset",
                        "offset":  1686601,
                        "virtualAddressHex":  "0x0059bc49",
                        "originalBytes":  "c744243886000000",
                        "patchedBytes":  "c744243818010000",
                        "rollbackBytes":  "c744243886000000",
                        "reason":  "FUN_0059b970 step-panel Y +146 (disp 0x38)"
                    },
                    {
                        "id":  "charsel-recenter-25",
                        "sourceExeSha256":  "5bdd64f1f9a8cca93f5b1002291d6a2c7e8f5ce555b062b8cb48337b96277d89",
                        "addressKind":  "offset",
                        "offset":  1690271,
                        "virtualAddressHex":  "0x0059ca9f",
                        "originalBytes":  "c74424282c010000",
                        "patchedBytes":  "c74424285c020000",
                        "rollbackBytes":  "c74424282c010000",
                        "reason":  "FUN_0059c940 step-panel X +304"
                    },
                    {
                        "id":  "charsel-recenter-26",
                        "sourceExeSha256":  "5bdd64f1f9a8cca93f5b1002291d6a2c7e8f5ce555b062b8cb48337b96277d89",
                        "addressKind":  "offset",
                        "offset":  1690279,
                        "virtualAddressHex":  "0x0059caa7",
                        "originalBytes":  "c744242c86000000",
                        "patchedBytes":  "c744242c18010000",
                        "rollbackBytes":  "c744242c86000000",
                        "reason":  "FUN_0059c940 step-panel Y +146"
                    },
                    {
                        "id":  "charsel-recenter-27",
                        "sourceExeSha256":  "5bdd64f1f9a8cca93f5b1002291d6a2c7e8f5ce555b062b8cb48337b96277d89",
                        "addressKind":  "offset",
                        "offset":  1691556,
                        "virtualAddressHex":  "0x0059cfa4",
                        "originalBytes":  "c74424282c010000",
                        "patchedBytes":  "c74424285c020000",
                        "rollbackBytes":  "c74424282c010000",
                        "reason":  "FUN_0059cee0 step-panel X +304"
                    },
                    {
                        "id":  "charsel-recenter-28",
                        "sourceExeSha256":  "5bdd64f1f9a8cca93f5b1002291d6a2c7e8f5ce555b062b8cb48337b96277d89",
                        "addressKind":  "offset",
                        "offset":  1691564,
                        "virtualAddressHex":  "0x0059cfac",
                        "originalBytes":  "c744242c86000000",
                        "patchedBytes":  "c744242c18010000",
                        "rollbackBytes":  "c744242c86000000",
                        "reason":  "FUN_0059cee0 step-panel Y +146"
                    },
                    {
                        "id":  "charsel-recenter-29",
                        "sourceExeSha256":  "5bdd64f1f9a8cca93f5b1002291d6a2c7e8f5ce555b062b8cb48337b96277d89",
                        "addressKind":  "offset",
                        "offset":  1692355,
                        "virtualAddressHex":  "0x0059d2c3",
                        "originalBytes":  "c74424282c010000",
                        "patchedBytes":  "c74424285c020000",
                        "rollbackBytes":  "c74424282c010000",
                        "reason":  "FUN_0059d200 step-panel X +304"
                    },
                    {
                        "id":  "charsel-recenter-30",
                        "sourceExeSha256":  "5bdd64f1f9a8cca93f5b1002291d6a2c7e8f5ce555b062b8cb48337b96277d89",
                        "addressKind":  "offset",
                        "offset":  1692363,
                        "virtualAddressHex":  "0x0059d2cb",
                        "originalBytes":  "c744242c86000000",
                        "patchedBytes":  "c744242c18010000",
                        "rollbackBytes":  "c744242c86000000",
                        "reason":  "FUN_0059d200 step-panel Y +146"
                    },
                    {
                        "id":  "charsel-recenter-31",
                        "sourceExeSha256":  "5bdd64f1f9a8cca93f5b1002291d6a2c7e8f5ce555b062b8cb48337b96277d89",
                        "addressKind":  "offset",
                        "offset":  1693466,
                        "virtualAddressHex":  "0x0059d71a",
                        "originalBytes":  "c74424302c010000",
                        "patchedBytes":  "c74424305c020000",
                        "rollbackBytes":  "c74424302c010000",
                        "reason":  "FUN_0059d520 취소/다음 버튼 패널 X +304 (disp 0x30)"
                    },
                    {
                        "id":  "charsel-recenter-32",
                        "sourceExeSha256":  "5bdd64f1f9a8cca93f5b1002291d6a2c7e8f5ce555b062b8cb48337b96277d89",
                        "addressKind":  "offset",
                        "offset":  1693474,
                        "virtualAddressHex":  "0x0059d722",
                        "originalBytes":  "c744243486000000",
                        "patchedBytes":  "c744243418010000",
                        "rollbackBytes":  "c744243486000000",
                        "reason":  "FUN_0059d520 취소/다음 버튼 패널 Y +146 (disp 0x34)"
                    },
                    {
                        "id":  "charsel-recenter-33",
                        "sourceExeSha256":  "5bdd64f1f9a8cca93f5b1002291d6a2c7e8f5ce555b062b8cb48337b96277d89",
                        "addressKind":  "offset",
                        "offset":  1697388,
                        "virtualAddressHex":  "0x0059e66c",
                        "originalBytes":  "c74424302c010000",
                        "patchedBytes":  "c74424305c020000",
                        "rollbackBytes":  "c74424302c010000",
                        "reason":  "FUN_0059df00 step-panel X +304 (disp 0x30)"
                    },
                    {
                        "id":  "charsel-recenter-34",
                        "sourceExeSha256":  "5bdd64f1f9a8cca93f5b1002291d6a2c7e8f5ce555b062b8cb48337b96277d89",
                        "addressKind":  "offset",
                        "offset":  1697396,
                        "virtualAddressHex":  "0x0059e674",
                        "originalBytes":  "c744243486000000",
                        "patchedBytes":  "c744243418010000",
                        "rollbackBytes":  "c744243486000000",
                        "reason":  "FUN_0059df00 step-panel Y +146 (disp 0x34)"
                    },
                    {
                        "id":  "charsel-recenter-35",
                        "sourceExeSha256":  "5bdd64f1f9a8cca93f5b1002291d6a2c7e8f5ce555b062b8cb48337b96277d89",
                        "addressKind":  "offset",
                        "offset":  1182354,
                        "virtualAddressHex":  "0x00520a92",
                        "originalBytes":  "c744242c5d020000",
                        "patchedBytes":  "c744242c8d030000",
                        "rollbackBytes":  "c744242c5d020000",
                        "reason":  "FUN_0051f8b0 SUB(능력치 우측 group0x47) X 605-\u003e909 (+304)"
                    },
                    {
                        "id":  "charsel-recenter-36",
                        "sourceExeSha256":  "5bdd64f1f9a8cca93f5b1002291d6a2c7e8f5ce555b062b8cb48337b96277d89",
                        "addressKind":  "offset",
                        "offset":  1182362,
                        "virtualAddressHex":  "0x00520a9a",
                        "originalBytes":  "c7442430ce000000",
                        "patchedBytes":  "c744243060010000",
                        "rollbackBytes":  "c7442430ce000000",
                        "reason":  "FUN_0051f8b0 SUB(group0x47) Y 206-\u003e352 (+146)"
                    },
                    {
                        "id":  "charsel-recenter-37",
                        "sourceExeSha256":  "5bdd64f1f9a8cca93f5b1002291d6a2c7e8f5ce555b062b8cb48337b96277d89",
                        "addressKind":  "offset",
                        "offset":  1662595,
                        "virtualAddressHex":  "0x00595e83",
                        "originalBytes":  "c74424082c010000",
                        "patchedBytes":  "c74424085c020000",
                        "rollbackBytes":  "c74424082c010000",
                        "reason":  "진영 라디오/엠블렘 패널 (FUN_00595e70) X 300-\u003e604 (+304, 프레임과 uniform). over-move 676은 우측 과도라 되돌림 — 정확 센터링은 블록 bbox 라이브 측정 후 결정(center-to-center)."
                    },
                    {
                        "id":  "charsel-recenter-38",
                        "sourceExeSha256":  "5bdd64f1f9a8cca93f5b1002291d6a2c7e8f5ce555b062b8cb48337b96277d89",
                        "addressKind":  "offset",
                        "offset":  1662603,
                        "virtualAddressHex":  "0x00595e8b",
                        "originalBytes":  "c744240c86000000",
                        "patchedBytes":  "c744240cf2000000",
                        "rollbackBytes":  "c744240c86000000",
                        "reason":  "진영 라디오/엠블렘 패널 Y 134-\u003e242 (+108). 콘텐츠 위로 38 보정(center-to-center, FUN_005989f0과 동일)."
                    }
                ]
}
